proofy_sdk/__init__.py
proofy_sdk/proofy.py
proofy_sdk_python-0.0.2.dist-info/LICENSE.txt
proofy_sdk_python-0.0.2.dist-info/METADATA
proofy_sdk_python-0.0.2.dist-info/WHEEL
proofy_sdk_python-0.0.2.dist-info/top_level.txt
proofy_sdk_python-0.0.2.dist-info/RECORD
