Metadata-Version: 2.1
Name: proofy-sdk-python
Version: 0.0.2
Summary: Proofy SDK
Home-page: https://proofy.me
Author: ProofyDevTeam
Author-email: dev@sbtkyc.io
Classifier: Programming Language :: Python :: 3
Classifier: License :: OSI Approved :: MIT License
Classifier: Operating System :: OS Independent
Requires-Python: >=3.6
License-File: LICENSE.txt
